mdtohtml/__init__.py
mdtohtml/__main__.py
mdtohtml/mdtohtml.py
mdtohtml-0.1.1.dist-info/DESCRIPTION.rst
mdtohtml-0.1.1.dist-info/METADATA
mdtohtml-0.1.1.dist-info/RECORD
mdtohtml-0.1.1.dist-info/WHEEL
mdtohtml-0.1.1.dist-info/entry_points.txt
mdtohtml-0.1.1.dist-info/metadata.json
mdtohtml-0.1.1.dist-info/top_level.txt
src/__init__.py
src/__main__.py
src/mdtohtml.py
